README.md
setup.py
mmvec/__init__.py
mmvec/heatmap.py
mmvec/multimodal.py
mmvec/util.py
mmvec.egg-info/PKG-INFO
mmvec.egg-info/SOURCES.txt
mmvec.egg-info/dependency_links.txt
mmvec.egg-info/entry_points.txt
mmvec.egg-info/not-zip-safe
mmvec.egg-info/requires.txt
mmvec.egg-info/top_level.txt
mmvec/q2/__init__.py
mmvec/q2/_method.py
mmvec/q2/_stats.py
mmvec/q2/_summary.py
mmvec/q2/_transformer.py
mmvec/q2/_visualizers.py
mmvec/q2/plugin_setup.py
mmvec/q2/assets/index.html
scripts/mmvec